<annotation>
	<folder>rose</folder>
	<filename>1402130395_0b89d76029.jpg</filename>
	<path>E:\Dowload\image\flowers-recognition\flowers\rose\1402130395_0b89d76029.jpg</path>
	<source>
		<database>Unknown</database>
	</source>
	<size>
		<width>500</width>
		<height>375</height>
		<depth>3</depth>
	</size>
	<segmented>0</segmented>
	<object>
		<name>rose</name>
		<pose>Unspecified</pose>
		<truncated>0</truncated>
		<difficult>0</difficult>
		<bndbox>
			<xmin>7</xmin>
			<ymin>2</ymin>
			<xmax>357</xmax>
			<ymax>332</ymax>
		</bndbox>
	</object>
	<object>
		<name>rose</name>
		<pose>Unspecified</pose>
		<truncated>0</truncated>
		<difficult>0</difficult>
		<bndbox>
			<xmin>260</xmin>
			<ymin>242</ymin>
			<xmax>398</xmax>
			<ymax>373</ymax>
		</bndbox>
	</object>
</annotation>
